refdict/__init__.py
refdict-3.3.0.dist-info/LICENSE
refdict-3.3.0.dist-info/METADATA
refdict-3.3.0.dist-info/WHEEL
refdict-3.3.0.dist-info/top_level.txt
refdict-3.3.0.dist-info/RECORD
