Metadata-Version: 2.1
Name: refdict
Version: 3.3.0
Summary: Using string as chain keys to realize chain access and reference access of dict in python
Home-page: https://github.com/DiscreteTom/refdict
Author: DiscreteTom
Author-email: discrete_tom@outlook.com
License: UNKNOWN
Platform: UNKNOWN
Classifier: Programming Language :: Python :: 3
Classifier: License :: OSI Approved :: GNU General Public License v3 (GPLv3)
Classifier: Operating System :: OS Independent
